tsm_realtime/__init__.py
tsm_realtime-0.1.5.dist-info/METADATA
tsm_realtime-0.1.5.dist-info/WHEEL
tsm_realtime-0.1.5.dist-info/top_level.txt
tsm_realtime-0.1.5.dist-info/RECORD
